fortune/__init__.py
fortune/main.py
pnu_fortune-1.0.3.data/data/man/man6/fortune.6.gz
pnu_fortune-1.0.3.dist-info/License
pnu_fortune-1.0.3.dist-info/METADATA
pnu_fortune-1.0.3.dist-info/WHEEL
pnu_fortune-1.0.3.dist-info/entry_points.txt
pnu_fortune-1.0.3.dist-info/top_level.txt
pnu_fortune-1.0.3.dist-info/RECORD
