Metadata-Version: 2.1
Name: pnu-fortune
Version: 1.0.3
Summary: print a random, hopefully interesting, adage
Home-page: https://github.com/HubTou/fortune/
Author: Hubert Tournier
Author-email: nobody@nowhere.invalid
License: BSD 3-Clause License
Project-URL: Bug Tracker, https://github.com/HubTou/fortune/issues
Keywords: pnu-project
Platform: UNKNOWN
Classifier: Development Status :: 5 - Production/Stable
Classifier: Environment :: Console
Classifier: Intended Audience :: End Users/Desktop
Classifier: License :: OSI Approved :: BSD License
Classifier: Natural Language :: English
Classifier: Operating System :: OS Independent
Classifier: Operating System :: POSIX :: BSD :: FreeBSD
Classifier: Operating System :: Microsoft :: Windows
Classifier: Programming Language :: Python :: 3
Classifier: Programming Language :: Python :: 3.0
Classifier: Programming Language :: Python :: 3.1
Classifier: Programming Language :: Python :: 3.2
Classifier: Programming Language :: Python :: 3.3
Classifier: Programming Language :: Python :: 3.4
Classifier: Programming Language :: Python :: 3.5
Classifier: Programming Language :: Python :: 3.6
Classifier: Programming Language :: Python :: 3.7
Classifier: Programming Language :: Python :: 3.8
Classifier: Programming Language :: Python :: 3.9
Classifier: Programming Language :: Python :: 3.10
Classifier: Topic :: Games/Entertainment
Classifier: Topic :: Games/Entertainment :: Fortune Cookies
Classifier: Topic :: System
Classifier: Topic :: Utilities
Requires-Python: >=3.0
License-File: License
Requires-Dist: pnu-strfile
Requires-Dist: pnu-rot13
Requires-Dist: fortunes-historical
Requires-Dist: fortunes-freebsd-classic
Requires-Dist: fortunes-python
Requires-Dist: fortunes-unix
